CHANGES
LICENSE
MANIFEST.in
README.rst
runtests.py
setup.cfg
setup.py
django_memoize_fork.egg-info/PKG-INFO
django_memoize_fork.egg-info/SOURCES.txt
django_memoize_fork.egg-info/dependency_links.txt
django_memoize_fork.egg-info/requires.txt
django_memoize_fork.egg-info/top_level.txt
docs/Makefile
docs/conf.py
docs/index.rst
docs/make.bat
docs/_static/flask-cache.png
docs/_themes/README
docs/_themes/flask_theme_support.py
docs/_themes/flask/theme.conf
docs/_themes/flask/static/flasky.css_t
docs/_themes/flask_small/layout.html
docs/_themes/flask_small/theme.conf
docs/_themes/flask_small/static/flasky.css_t
memoize/__init__.py
memoize/_compat.py
memoize/models.py