Metadata-Version: 1.1
Name: django-memoize-fork
Version: 1.0
Summary: An implementation of memoization technique for Django.
Home-page: https://github.com/tvavrys/django-memoize
Author: Thomas Vavrys
Author-email: tvavrys@sleio.com
License: BSD License
Platform: UNKNOWN
Classifier: Environment :: Web Environment
Classifier: Framework :: Django
Classifier: Intended Audience :: Developers
Classifier: License :: OSI Approved :: BSD License
Classifier: Operating System :: OS Independent
Classifier: Programming Language :: Python
Classifier: Topic :: Internet :: WWW/HTTP
Classifier: Topic :: Internet :: WWW/HTTP :: Dynamic Content
